doctor_trans/__init__.py
doctor_trans/trans.c
doctor_trans/trans.cp311-win_amd64.pyd
doctor_trans-1.0.3.dist-info/METADATA
doctor_trans-1.0.3.dist-info/WHEEL
doctor_trans-1.0.3.dist-info/top_level.txt
doctor_trans-1.0.3.dist-info/RECORD
