Metadata-Version: 2.1
Name: doctor_trans
Version: 1.0.3
Summary: This package translate whole dataframe in any language without any limits.
Home-page: 
Author: Nirmal Patel
Author-email: nirmalpatel1705@gmail.com
Requires-Dist: pandas
Requires-Dist: requests
